{
  "node_id": "tos.concept.stability",
  "node_type": "concept",
  "source_anchor": "Included here as the bounded tension companion inside the calibration-family pilot",
  "key_terms": [
    "stability",
    "fixity",
    "preservation"
  ],
  "distilled_thesis": "Stability names the preserving counterforce against which becoming and overcoming can be read more sharply inside this pilot route.",
  "lineage_relations": [
    {
      "relation": "tension",
      "target_ref": "tos.concept.becoming"
    },
    {
      "relation": "parallel",
      "target_ref": "tos.lineage.calibration-family.becoming-to-overcoming"
    }
  ],
  "interpretation_layers": [
    "source_linked",
    "distilled_thesis",
    "cross_text_comparison"
  ]
}
